setup.py
planbox/__init__.py
planbox/util.py
python_planbox.egg-info/PKG-INFO
python_planbox.egg-info/SOURCES.txt
python_planbox.egg-info/dependency_links.txt
python_planbox.egg-info/requires.txt
python_planbox.egg-info/top_level.txt