Metadata-Version: 1.0
Name: python-planbox
Version: 0.0.1
Summary: Python interface to the planbox API
Home-page: https://github.com/stephenyoung/python-planbox
Author: Stephen Young
Author-email: stephen@tryllo.com
License: UNKNOWN
Platform: UNKNOWN
